openpoiservice/__init__.py
openpoiservice/server/__init__.py
openpoiservice/server/config.py
openpoiservice/server/api/__init__.py
openpoiservice/server/api/api_exceptions.py
openpoiservice/server/api/query_builder.py
openpoiservice/server/api/query_info.py
openpoiservice/server/api/views.py
openpoiservice/server/categories/__init__.py
openpoiservice/server/categories/categories.py
openpoiservice/server/db_import/__init__.py
openpoiservice/server/db_import/models.py
openpoiservice/server/db_import/objects.py
openpoiservice/server/db_import/parse_osm.py
openpoiservice/server/db_import/parser.py
openpoiservice/server/utils/__init__.py
openpoiservice/server/utils/decorators.py
openpoiservice/server/utils/geometries.py
openpoiservice/tests/__init__.py
openpoiservice/tests/base.py
openpoiservice/tests/helpers.py
openpoiservice/tests/test_category_list.py
openpoiservice/tests/test_pois.py
openpoiservice/tests/test_stats.py
openpoiservice-0.1.7.dist-info/METADATA
openpoiservice-0.1.7.dist-info/RECORD
openpoiservice-0.1.7.dist-info/WHEEL
openpoiservice-0.1.7.dist-info/top_level.txt
