Metadata-Version: 2.1
Name: openpoiservice
Version: 0.1.7
Summary: POI service consuming OpenStreetMap data
Home-page: https://github.com/GIScience/openpoiservice
Author: Timothy Ellersiek
Author-email: timothy@openrouteservice.org
License: UNKNOWN
Project-URL: Bug Reports, https://github.com/GIScience/openpoiservice/issues
Project-URL: Source, https://github.com/GIScience/openpoiservice
Keywords: OSM ORS openrouteservice openstreetmap POI points of interest
Platform: UNKNOWN
Classifier: Development Status :: 4 - Beta
Classifier: Intended Audience :: Developers
Classifier: Topic :: Software Development :: Build Tools
Classifier: License :: OSI Approved :: MIT License
Classifier: Programming Language :: Python :: 3.5
Classifier: Programming Language :: Python :: 3.6
